micro_aes/__init__.py
micro_aes/aes.py
micro_aes/constants.py
micro_aes-2021.6.dist-info/LICENSE
micro_aes-2021.6.dist-info/METADATA
micro_aes-2021.6.dist-info/WHEEL
micro_aes-2021.6.dist-info/top_level.txt
micro_aes-2021.6.dist-info/RECORD
